pdf_export_notes_to_markdown.py
pdf_export_notes_to_markdown-0.1.0.dist-info/METADATA
pdf_export_notes_to_markdown-0.1.0.dist-info/WHEEL
pdf_export_notes_to_markdown-0.1.0.dist-info/entry_points.txt
pdf_export_notes_to_markdown-0.1.0.dist-info/top_level.txt
pdf_export_notes_to_markdown-0.1.0.dist-info/RECORD
