Metadata-Version: 2.4
Name: pdf-export-notes-to-markdown
Version: 0.1.0
Summary: Add your description here
Requires-Python: >=3.10
Requires-Dist: pymupdf>=1.24.11
